darbiadev_onsite/__init__.py
darbiadev_onsite/vendor/fmjdbc.jar
darbiadev_onsite-1.0.0.dist-info/LICENSE
darbiadev_onsite-1.0.0.dist-info/METADATA
darbiadev_onsite-1.0.0.dist-info/WHEEL
darbiadev_onsite-1.0.0.dist-info/top_level.txt
darbiadev_onsite-1.0.0.dist-info/RECORD
